LICENSE
MANIFEST.in
README.rst
setup.py
tests/__init__.py
tests/conftest.py
tests/test_blog.py
tests/test_blog_models.py
tests/test_blog_views.py
tests/test_pages_models.py
tests/test_templatetags.py
tests/urls.py
tests/utils.py
tests/recipes/__init__.py
tests/recipes/mommy_recipes.py
wagtail_box/__init__.py
wagtail_box/fields.py
wagtail_box/blog/__init__.py
wagtail_box/blog/models.py
wagtail_box/blog/migrations/0001_initial.py
wagtail_box/blog/migrations/__init__.py
wagtail_box/blog/templates/blog/blog.html
wagtail_box/blog/templates/blog/post.html
wagtail_box/blog/templatetags/__init__.py
wagtail_box/blog/templatetags/blog_tags.py
wagtail_box/pages/__init__.py
wagtail_box/pages/models.py
wagtail_box/pages/migrations/0001_initial.py
wagtail_box/pages/migrations/__init__.py
wagtail_box/pages/templates/pages/static_page.html
wagtail_box/templates/partials/streamfield.html
wagtail_nesting_box.egg-info/PKG-INFO
wagtail_nesting_box.egg-info/SOURCES.txt
wagtail_nesting_box.egg-info/dependency_links.txt
wagtail_nesting_box.egg-info/not-zip-safe
wagtail_nesting_box.egg-info/top_level.txt