Metadata-Version: 1.1
Name: wagtail-nesting-box
Version: 0.2.1
Summary: Wagtail nesting box
Home-page: https://github.com/palazzem/wagtail-nesting-box
Author: Emanuele Palazzetti
Author-email: hello@palazzetti.me
License: BSD
Keywords: django wagtail
Platform: UNKNOWN
Classifier: Development Status :: 4 - Beta
Classifier: Environment :: Web Environment
Classifier: Framework :: Django
Classifier: License :: OSI Approved :: BSD License
Classifier: Operating System :: OS Independent
Classifier: Programming Language :: Python :: 2.7
Classifier: Programming Language :: Python :: 3.3
Classifier: Programming Language :: Python :: 3.4
Classifier: Programming Language :: Python :: 3.5
Classifier: Topic :: Software Development :: Libraries :: Python Modules
Classifier: Framework :: Django
Classifier: Framework :: Django :: 1.8
Classifier: Framework :: Django :: 1.9
